.gitignore
LICENSE.txt
MANIFEST.in
README.rst
requirements.txt
setup.cfg
setup.py
pyIsis/VERSION
pyIsis/__init__.py
pyIsis/connection.py
pyIsis/filesystem.py
pyIsis/utils.py
pyIsis.egg-info/PKG-INFO
pyIsis.egg-info/SOURCES.txt
pyIsis.egg-info/dependency_links.txt
pyIsis.egg-info/not-zip-safe
pyIsis.egg-info/requires.txt
pyIsis.egg-info/top_level.txt