Metadata-Version: 1.1
Name: pyIsis
Version: 0.2.3
Summary: Python wrapper for Avid Isis Client Management Console
Home-page: http://github.com/predat/pyIsis
Author: Sylvain Maziere
Author-email: sylvain@predat.fr
License: MIT
Download-URL: https://github.com/predat/pyIsis/tarball/0.2.3
Keywords: avid isis client mount workspace
Platform: UNKNOWN
Classifier: Development Status :: 4 - Beta
Classifier: Environment :: MacOS X
Classifier: Intended Audience :: Information Technology
Classifier: Intended Audience :: System Administrators
Classifier: License :: OSI Approved :: MIT License
Classifier: Natural Language :: English
Classifier: Programming Language :: Python
Classifier: Topic :: System :: Systems Administration
Classifier: Topic :: System :: Filesystems
Classifier: Topic :: Utilities
